setup.cfg
setup.py
aliyun/__init__.py
aliyun/log/__init__.py
aliyun/log/acl_config.py
aliyun/log/acl_response.py
aliyun/log/cursor_response.py
aliyun/log/cursor_time_response.py
aliyun/log/gethistogramsrequest.py
aliyun/log/gethistogramsresponse.py
aliyun/log/getlogsrequest.py
aliyun/log/getlogsresponse.py
aliyun/log/histogram.py
aliyun/log/index_config.py
aliyun/log/index_config_response.py
aliyun/log/listlogstoresrequest.py
aliyun/log/listlogstoresresponse.py
aliyun/log/listtopicsrequest.py
aliyun/log/listtopicsresponse.py
aliyun/log/log_logs_pb2.py
aliyun/log/logclient.py
aliyun/log/logexception.py
aliyun/log/logitem.py
aliyun/log/logrequest.py
aliyun/log/logresponse.py
aliyun/log/logstore_config_response.py
aliyun/log/logtail_config_detail.py
aliyun/log/logtail_config_response.py
aliyun/log/machine_group_detail.py
aliyun/log/machinegroup_response.py
aliyun/log/project_response.py
aliyun/log/pulllog_response.py
aliyun/log/putlogsrequest.py
aliyun/log/putlogsresponse.py
aliyun/log/queriedlog.py
aliyun/log/shard_response.py
aliyun/log/shipper_config.py
aliyun/log/shipper_response.py
aliyun/log/util.py
suuze_log/__init__.py
suuze_log/handlers.py
suuze_log_service.egg-info/PKG-INFO
suuze_log_service.egg-info/SOURCES.txt
suuze_log_service.egg-info/dependency_links.txt
suuze_log_service.egg-info/requires.txt
suuze_log_service.egg-info/top_level.txt