Metadata-Version: 1.1
Name: suuze-log-service
Version: 0.0.2
Summary: Log service Python client SDK integrating aliyun log service
Home-page: https://github.com/GridSafe/suuze-ali-loghub
Author: suuze and sls_dev
Author-email: UNKNOWN
License: UNKNOWN
Platform: UNKNOWN
Classifier: Development Status :: 5 - Production/Stable
Classifier: Programming Language :: Python :: 3.5
